<system>
	<name>K2-78</name>
	<rightascension>03 48 54</rightascension>
	<declination>+13 29 01</declination>
	<star>
		<name>K2-78</name>
		<radius errorminus="0.12" errorplus="0.12">0.88</radius>
		<magV errorminus="0.020">12.191</magV>
		<mass errorminus="0.09" errorplus="0.09">0.90</mass>
		<temperature errorminus="203.00" errorplus="203.00">5729.00</temperature>
		<planet>
			<name>K2-78 b</name>
			<semimajoraxis errorminus="0.001100" errorplus="0.001100">0.032800</semimajoraxis>
			<period errorminus="0.00027000" errorplus="0.00027000">2.29016000</period>
			<radius errorminus="0.020" errorplus="0.020">0.127</radius>
			<discoverymethod>Transit</discoverymethod>
			<discoveryyear>2016</discoveryyear>
			<lastupdate>16/07/18</lastupdate>
			<transittime errorminus=".004300" errorplus="0.004300" unit="BJD_TDB">2457065.144400</transittime>
		</planet>
	</star>
</system>